iota_mnemonic/__init__.py
iota_mnemonic/__main__.py
iota_mnemonic/iotamnemonic.py
iota_mnemonic-0.2.1.dist-info/LICENSE
iota_mnemonic-0.2.1.dist-info/WHEEL
iota_mnemonic-0.2.1.dist-info/METADATA
iota_mnemonic-0.2.1.dist-info/RECORD
