Metadata-Version: 1.2
Name: iota_mnemonic
Version: 0.2.1
Summary: Generate, recover IOTA seed from Bitcoin BIP39 mnemonic
Home-page: https://github.com/mlouielu/iota-mnemonic
License: UNKNOWN
Author: Louie Lu
Author-email: git@louie.lu
Maintainer: Louie Lu
Maintainer-email: git@louie.lu
Requires-Python: >= 3
Classifier: License :: OSI Approved :: MIT License
Classifier: Programming Language :: Python :: 3
Classifier: Topic :: Software Development :: Libraries :: Python Modules
Classifier: Intended Audience :: Developers
Requires-Dist: pyota (>= 2.0.1)
Requires-Dist: mnemonic (>= 0.18)
